[
  {
    "taskID": "4cb332f2-68fe-455c-9bd4-1a201921e302",
    "name": "nice task",
    "assignee": "",
    "description": "",
    "priority": "-",
    "length": "-",
    "currentProgress": "To Do",
    "sprint": 2
  },
  {
    "taskID": "734a7fa6-6525-4116-8bc1-32bbf20baeaf",
    "name": "700 20's",
    "assignee": "jaden",
    "description": "",
    "priority": "-",
    "length": "-",
    "currentProgress": "In Progress",
    "sprint": 2
  },
  {
    "taskID": "bf348771-b2ca-4e4a-9e76-6d50987a256b",
    "name": "test task",
    "assignee": "",
    "description": "",
    "priority": "-",
    "length": "-",
    "currentProgress": "Done",
    "sprint": 1
  }
]